logab/__init__.py
logab/log_utils.py
logab-1.2.4.dist-info/licenses/LICENSE
logab-1.2.4.dist-info/METADATA
logab-1.2.4.dist-info/WHEEL
logab-1.2.4.dist-info/top_level.txt
logab-1.2.4.dist-info/RECORD
