Metadata-Version: 2.4
Name: logab
Version: 1.2.4
Summary: A lightweight Python package for logging with auto-balance (ab) formatting.
Author-email: Nam Kha Nguyen <namkha1032@gmail.com>
License: MIT License
Project-URL: Homepage, https://github.com/namkha1032/logab
Project-URL: Repository, https://github.com/namkha1032/logab
Requires-Python: >=3.8
License-File: LICENSE
Dynamic: license-file
